{
  "admin1": [
    {
      "geo_id": "8801a6d7-78da-424f-908d-23d7cf948a20",
      "country": "Democratic Republic of the Congo",
      "iso3": "COD",
      "admin1": "Nord-Kivu",
      "admin2": null,
      "lat": -0.9,
      "lon": 29.2
    },
    {
      "geo_id": "bf3cfda5-5a5e-42f9-8760-05b50c40b972",
      "country": "Democratic Republic of the Congo",
      "iso3": "COD",
      "admin1": "Sud-Kivu",
      "admin2": null,
      "lat": -2.5,
      "lon": 28.8
    },
    {
      "geo_id": "e04ac541-1bb9-4154-9fba-bfcddf0f1fed",
      "country": "Democratic Republic of the Congo",
      "iso3": "COD",
      "admin1": "Ituri",
      "admin2": null,
      "lat": 1.6,
      "lon": 30.5
    },
    {
      "geo_id": "26c039a0-c75d-49ad-8a5c-235d41363914",
      "country": "Democratic Republic of the Congo",
      "iso3": "COD",
      "admin1": "Kasaï",
      "admin2": null,
      "lat": -5.1,
      "lon": 22.4
    },
    {
      "geo_id": "3f241b32-8614-4e1b-94ae-01054fbe93f7",
      "country": "Democratic Republic of the Congo",
      "iso3": "COD",
      "admin1": "Kinshasa",
      "admin2": null,
      "lat": -4.3,
      "lon": 15.3
    },
    {
      "geo_id": "d2cb7dd1-d622-4398-ab79-617bf9e00bdf",
      "country": "Democratic Republic of the Congo",
      "iso3": "COD",
      "admin1": "Tanganyika",
      "admin2": null,
      "lat": -6.2,
      "lon": 29.8
    }
  ]
}